autocontext/__init__.py
autocontext/autocontext.py
autocontext/models.py
iolanta/__init__.py
iolanta/cli/__init__.py
iolanta/cli/main.py
iolanta/cli/pretty_print.py
iolanta/context.py
iolanta/conversions.py
iolanta/ensure_is_context.py
iolanta/entry_points.py
iolanta/errors.py
iolanta/facet.py
iolanta/facets/__init__.py
iolanta/facets/base.py
iolanta/facets/by_environment.py
iolanta/facets/by_instance.py
iolanta/facets/by_literal_datatype.py
iolanta/facets/by_type.py
iolanta/facets/errors.py
iolanta/facets/for_literal.py
iolanta/facets/sparql/find_facet_by_instance_types.sparql
iolanta/facets/sparql/find_facet_for_literal.sparql
iolanta/graph_providers/__init__.py
iolanta/graph_providers/base.py
iolanta/graph_providers/errors.py
iolanta/graph_providers/find.py
iolanta/iolanta.py
iolanta/loaders/__init__.py
iolanta/loaders/base.py
iolanta/loaders/data_type_choice.py
iolanta/loaders/errors.py
iolanta/loaders/http.py
iolanta/loaders/local_directory.py
iolanta/loaders/local_file.py
iolanta/loaders/scheme_choice.py
iolanta/models.py
iolanta/namespaces.py
iolanta/parsers/__init__.py
iolanta/parsers/base.py
iolanta/parsers/errors.py
iolanta/parsers/json.py
iolanta/parsers/markdown.py
iolanta/parsers/yaml.py
iolanta/reformat_blank_nodes.py
iolanta/renderer.py
iolanta/shortcuts.py
ldflex/__init__.py
ldflex/ldflex.py
mkdocs_iolanta/__init__.py
mkdocs_iolanta/cli/__init__.py
mkdocs_iolanta/cli/context.py
mkdocs_iolanta/cli/formatters/__init__.py
mkdocs_iolanta/cli/formatters/choose.py
mkdocs_iolanta/cli/formatters/csv.py
mkdocs_iolanta/cli/formatters/json.py
mkdocs_iolanta/cli/formatters/node_to_qname.py
mkdocs_iolanta/cli/formatters/pretty.py
mkdocs_iolanta/cli/main.py
mkdocs_iolanta/cli/show.py
mkdocs_iolanta/cli/sparql.py
mkdocs_iolanta/cli/update.py
mkdocs_iolanta/conversions.py
mkdocs_iolanta/data/foaf/foaf.json
mkdocs_iolanta/data/foaf/named-context.json
mkdocs_iolanta/data/iolanta/named-context.json
mkdocs_iolanta/data/octa/named-context.json
mkdocs_iolanta_tables-1.2.0.dist-info/METADATA
mkdocs_iolanta_tables-1.2.0.dist-info/entry_points.txt
mkdocs_iolanta_tables-1.2.0.dist-info/WHEEL
mkdocs_iolanta_tables-1.2.0.dist-info/LICENSE
mkdocs_iolanta_tables-1.2.0.dist-info/RECORD
